fpv_auto_trimmer.py
fpv_auto_trimmer-0.1.2.dist-info/LICENSE
fpv_auto_trimmer-0.1.2.dist-info/METADATA
fpv_auto_trimmer-0.1.2.dist-info/WHEEL
fpv_auto_trimmer-0.1.2.dist-info/entry_points.txt
fpv_auto_trimmer-0.1.2.dist-info/top_level.txt
fpv_auto_trimmer-0.1.2.dist-info/RECORD
