Metadata-Version: 2.2
Name: fpv-auto-trimmer
Version: 0.1.2
Summary: Automatically trim FPV drone footage based on motion detection.
Requires-Python: >=3.8
License-File: LICENSE
Requires-Dist: opencv-python
Requires-Dist: numpy
Provides-Extra: dev
Requires-Dist: pylint; extra == "dev"
Requires-Dist: black; extra == "dev"
Requires-Dist: isort; extra == "dev"
Requires-Dist: build; extra == "dev"
